augpathlib/__init__.py
augpathlib/caches.py
augpathlib/core.py
augpathlib/exceptions.py
augpathlib/meta.py
augpathlib/package.py
augpathlib/pyads.py
augpathlib/remotes.py
augpathlib/repo.py
augpathlib/repo_patch.py
augpathlib/swap.py
augpathlib/utils.py
augpathlib/zip.py
augpathlib-0.0.34.dist-info/licenses/LICENSE
augpathlib-0.0.34.dist-info/METADATA
augpathlib-0.0.34.dist-info/WHEEL
augpathlib-0.0.34.dist-info/top_level.txt
augpathlib-0.0.34.dist-info/RECORD
