Metadata-Version: 2.4
Name: augpathlib
Version: 0.0.34
Summary: Augmented pathlib. Everything else you could do with a path.
Home-page: https://github.com/tgbugs/augpathlib
Author: Tom Gillespie
Author-email: tgbugs@gmail.com
License: MIT
Keywords: pathlib path paths
Classifier: Development Status :: 3 - Alpha
Classifier: License :: OSI Approved :: MIT License
Classifier: Programming Language :: Python :: 3.7
Classifier: Programming Language :: Python :: 3.8
Classifier: Programming Language :: Python :: 3.9
Classifier: Programming Language :: Python :: 3.10
Classifier: Programming Language :: Python :: 3.11
Classifier: Programming Language :: Python :: 3.12
Classifier: Programming Language :: Python :: 3.13
Classifier: Programming Language :: Python :: 3.14
Classifier: Programming Language :: Python :: Implementation :: CPython
Classifier: Programming Language :: Python :: Implementation :: PyPy
Classifier: Operating System :: POSIX :: Linux
Classifier: Operating System :: MacOS :: MacOS X
Classifier: Operating System :: Microsoft :: Windows
Requires-Python: >=3.7
License-File: LICENSE
Requires-Dist: file_magic; os_name != "nt"
Requires-Dist: pexpect>=4.7.0
Requires-Dist: python-dateutil
Requires-Dist: pyxattr; os_name != "nt"
Requires-Dist: terminaltables3
Provides-Extra: dev
Requires-Dist: pytest-cov; extra == "dev"
Requires-Dist: wheel; extra == "dev"
Provides-Extra: package
Requires-Dist: setuptools; extra == "package"
Requires-Dist: packaging; extra == "package"
Requires-Dist: requests; extra == "package"
Provides-Extra: repo
Requires-Dist: gitpython; extra == "repo"
Provides-Extra: test
Requires-Dist: pytest; extra == "test"
Requires-Dist: gitpython; extra == "test"
Requires-Dist: setuptools; extra == "test"
Requires-Dist: packaging; extra == "test"
Requires-Dist: requests; extra == "test"
Dynamic: author
Dynamic: author-email
Dynamic: classifier
Dynamic: description
Dynamic: description-content-type
Dynamic: home-page
Dynamic: keywords
Dynamic: license
Dynamic: license-file
Dynamic: provides-extra
Dynamic: requires-dist
Dynamic: requires-python
Dynamic: summary
